data_gov_fetcher/__init__.py
data_gov_fetcher/cli.py
data_gov_fetcher-0.1.0.dist-info/licenses/LICENSE
data_gov_fetcher-0.1.0.dist-info/METADATA
data_gov_fetcher-0.1.0.dist-info/WHEEL
data_gov_fetcher-0.1.0.dist-info/entry_points.txt
data_gov_fetcher-0.1.0.dist-info/top_level.txt
data_gov_fetcher-0.1.0.dist-info/RECORD
