Metadata-Version: 2.4
Name: data-gov-fetcher
Version: 0.1.0
Summary: A CLI tool to fetch datasets from Data.gov CKAN API
Author: brainiacpol
Author-email: work4product@gmail.com
Classifier: Programming Language :: Python :: 3
Classifier: License :: OSI Approved :: MIT License
Classifier: Operating System :: OS Independent
Requires-Python: >=3.6
License-File: LICENSE
Requires-Dist: requests
Dynamic: author
Dynamic: author-email
Dynamic: classifier
Dynamic: license-file
Dynamic: requires-dist
Dynamic: requires-python
Dynamic: summary
